discuit/__init__.py
discuit/calculations.py
discuit/clustering.py
discuit/command_line.py
discuit/data.py
discuit/run.py
discuit/save_stats.py
discuit/write.py
tests/__init__.py
tests/test_my_module.py
discuit-0.4.1.dist-info/LICENSE
discuit-0.4.1.dist-info/METADATA
discuit-0.4.1.dist-info/NOTICE
discuit-0.4.1.dist-info/WHEEL
discuit-0.4.1.dist-info/entry_points.txt
discuit-0.4.1.dist-info/top_level.txt
discuit-0.4.1.dist-info/RECORD
