Metadata-Version: 2.1
Name: discuit
Version: 0.4.1
Summary: Dynamic item set clustering UI tool: The goal of this package is to split datasets (e.g. words defined by several variables) into subsets that are as comparable as possible.
Home-page: https://github.com/doerte/discuit-project
Author: Dörte de Kok
Author-email: me@doerte.eu
Project-URL: Bug Tracker, https://github.com/doerte/discuit-project/issues
Keywords: clustering
Classifier: Development Status :: 4 - Beta
Classifier: Intended Audience :: Science/Research
Classifier: License :: OSI Approved :: Apache Software License
Classifier: Natural Language :: English
Classifier: Programming Language :: Python :: 3
Classifier: Programming Language :: Python :: 3.7
Classifier: Programming Language :: Python :: 3.8
Classifier: Programming Language :: Python :: 3.9
Classifier: Programming Language :: Python :: 3.10
Classifier: Programming Language :: Python :: 3.11
Requires-Python: >=3.7
License-File: LICENSE
License-File: NOTICE
Requires-Dist: argparse >=1.4.0dev
Requires-Dist: pathlib >=1.0.0
Requires-Dist: typing >=3.7.4.0
Requires-Dist: pandas >=1.3.0
Requires-Dist: kmodes >=0.12.0
Requires-Dist: scipy >=1.7.0
Requires-Dist: scikit-learn >=1.0.0
Provides-Extra: dev
Requires-Dist: bump2version ; extra == 'dev'
Requires-Dist: coverage[toml] ; extra == 'dev'
Requires-Dist: prospector[with_pyroma] ; extra == 'dev'
Requires-Dist: isort ; extra == 'dev'
Requires-Dist: pytest ; extra == 'dev'
Requires-Dist: pytest-cov ; extra == 'dev'
Requires-Dist: sphinx ; extra == 'dev'
Requires-Dist: sphinx-rtd-theme ; extra == 'dev'
Requires-Dist: sphinx-autoapi ; extra == 'dev'
Requires-Dist: tox ; extra == 'dev'
Requires-Dist: myst-parser ; extra == 'dev'
Provides-Extra: publishing
Requires-Dist: twine ; extra == 'publishing'
Requires-Dist: wheel ; extra == 'publishing'
